flood/__init__.py
flood/__main__.py
flood/spec.py
flood/cli/cli_run.py
flood/cli/ls_command.py
flood/cli/print_command.py
flood/cli/report_command.py
flood/cli/root_command.py
flood/cli/samples_collect_command.py
flood/cli/samples_download_command.py
flood/cli/samples_ls_command.py
flood/cli/update_command.py
flood/cli/version_command.py
flood/generators/__init__.py
flood/generators/rng_utils.py
flood/generators/object_generators/__init__.py
flood/generators/object_generators/address_generators.py
flood/generators/object_generators/block_generators.py
flood/generators/object_generators/call_generators.py
flood/generators/object_generators/slot_generators.py
flood/generators/object_generators/timing_generators.py
flood/generators/object_generators/transaction_generators.py
flood/generators/raw_data_sources/__init__.py
flood/generators/raw_data_sources/raw_data_spec.py
flood/generators/raw_data_sources/raw_download_utils.py
flood/generators/raw_data_sources/raw_gather_utils.py
flood/generators/raw_data_sources/raw_sample_loading.py
flood/generators/test_generators/__init__.py
flood/generators/test_generators/address_test_generators.py
flood/generators/test_generators/block_test_generators.py
flood/generators/test_generators/contract_test_generators.py
flood/generators/test_generators/generic_test_generators.py
flood/generators/test_generators/log_test_generators.py
flood/generators/test_generators/multi_test_generators.py
flood/generators/test_generators/trace_test_generators.py
flood/generators/test_generators/transaction_test_generators.py
flood/ops/__init__.py
flood/ops/installation_utils.py
flood/ops/update_utils.py
flood/runners/__init__.py
flood/runners/generic_runner/__init__.py
flood/runners/generic_runner/generic_runner_execution.py
flood/runners/multi_runner/__init__.py
flood/runners/multi_runner/multi_runner_io.py
flood/runners/single_runner/__init__.py
flood/runners/single_runner/single_runner_execution.py
flood/runners/single_runner/single_runner_io.py
paradigm_flood-0.3.1.dist-info/entry_points.txt
paradigm_flood-0.3.1.dist-info/LICENSE-APACHE
paradigm_flood-0.3.1.dist-info/LICENSE-MIT
paradigm_flood-0.3.1.dist-info/WHEEL
paradigm_flood-0.3.1.dist-info/METADATA
paradigm_flood-0.3.1.dist-info/RECORD
