Metadata-Version: 2.1
Name: paradigm-flood
Version: 0.3.1
Summary: tool for benchmarking RPC endpoints
Requires-Python: >=3.7
Classifier: Development Status :: 4 - Beta
Classifier: Intended Audience :: Developers
Classifier: Intended Audience :: Financial and Insurance Industry
Classifier: Intended Audience :: Science/Research
Classifier: License :: OSI Approved :: Apache Software License
Classifier: License :: OSI Approved :: MIT License
Classifier: Natural Language :: English
Classifier: Operating System :: MacOS
Classifier: Operating System :: Microsoft :: Windows
Classifier: Operating System :: POSIX :: Linux
Classifier: Programming Language :: Python :: 3.7
Classifier: Programming Language :: Python :: 3.8
Classifier: Programming Language :: Python :: 3.9
Classifier: Programming Language :: Python :: 3.10
Classifier: Programming Language :: Python :: 3.11
Classifier: Typing :: Typed
Requires-Dist: checkthechain >= 0.3.9, <0.4.0
Requires-Dist: ipykernel > 6, <7
Requires-Dist: ipython_genutils > 0.1, <1
Requires-Dist: matplotlib >= 3.7.1, <4
Requires-Dist: nbconvert > 6, <7
Requires-Dist: nbformat >= 5.8.0, <6
Requires-Dist: numpy >=1.19.0, <1.25
Requires-Dist: orjson >=3.0.0, < 4
Requires-Dist: paradigm-data-portal >= 0.2.2, <0.3
Requires-Dist: polars >= 0.17
Requires-Dist: requests >=2.20.0, <3
Requires-Dist: toolcli >=0.6.16, <0.7
Requires-Dist: toolplot >= 0.3.4, <0.4
Requires-Dist: toolstr >=0.9.7, <0.10
Requires-Dist: tqdm >=4.65.0, <5
Requires-Dist: typing-extensions >=4.2.0, <5
Requires-Dist: mypy ==1.2.0 ; extra == "test"
Requires-Dist: mypy_extensions >= 1.0.0, <1.1.0 ; extra == "test"
Requires-Dist: pytest >=6, <7 ; extra == "test"
Requires-Dist: types-tqdm >= 4.65.0.1, <5 ; extra == "test"
Provides-Extra: test
